glucosedao_client/__init__.py
glucosedao_client/app.py
glucosedao_client/cli.py
glucosedao_client/client.py
glucosedao_client/server.py
glucosedao_client-0.3.1.dist-info/METADATA
glucosedao_client-0.3.1.dist-info/WHEEL
glucosedao_client-0.3.1.dist-info/entry_points.txt
glucosedao_client-0.3.1.dist-info/licenses/LICENSE
glucosedao_client-0.3.1.dist-info/RECORD
