Metadata-Version: 2.4
Name: glucosedao-client
Version: 0.3.1
Summary: Reference client implementation for GluRPC - provides Python SDK and Gradio web interface for glucose prediction service.
License-File: LICENSE
Requires-Python: >=3.11
Requires-Dist: cgm-format>=0.5
Requires-Dist: gradio<6.0,>=4.0
Requires-Dist: httpx>=0.27.0
Requires-Dist: matplotlib>=3.10.7
Requires-Dist: pillow>=10.0.0
Requires-Dist: plotly<6.0
Requires-Dist: typer>=0.12.0
Requires-Dist: uvicorn>=0.30.0
Provides-Extra: dev
Requires-Dist: glurpc>=0.6.2; extra == 'dev'
Requires-Dist: pytest>=7.0.0; extra == 'dev'
